{
    "type": "state",
    "state": "de",
    "data": 
        [
          {
            "Year": 1980,
            "Population": 594779,
            "Violent crime total": 2824,
            "Murder and nonnegligent Manslaughter": 41,
            "Legacy rape /1": 144,
            "Revised rape /2": "",
            "Robbery": 815,
            "Aggravated assault": 1824,
            "Property crime total": 37482,
            "Burglary": 9698,
            "Larceny-theft": 25077,
            "Motor vehicle theft": 2707,
            "Violent Crime rate": 474.8,
            "Murder and nonnegligent manslaughter rate": 6.9,
            "Legacy rape rate /1": 24.2,
            "Robbery rate": 137,
            "Aggravated assault rate": 306.7,
            "Property crime rate": 6301.8,
            "Burglary rate": 1630.5,
            "Larceny-theft rate": 4216.2,
            "Motor vehicle theft rate": 455.1
          },
          {
            "Year": 1981,
            "Population": 598000,
            "Violent crime total": 3044,
            "Murder and nonnegligent Manslaughter": 40,
            "Legacy rape /1": 170,
            "Revised rape /2": "",
            "Robbery": 844,
            "Aggravated assault": 1990,
            "Property crime total": 36958,
            "Burglary": 9627,
            "Larceny-theft": 24759,
            "Motor vehicle theft": 2572,
            "Violent Crime rate": 509,
            "Murder and nonnegligent manslaughter rate": 6.7,
            "Legacy rape rate /1": 28.4,
            "Robbery rate": 141.1,
            "Aggravated assault rate": 332.8,
            "Property crime rate": 6180.3,
            "Burglary rate": 1609.9,
            "Larceny-theft rate": 4140.3,
            "Motor vehicle theft rate": 430.1
          },
          {
            "Year": 1982,
            "Population": 602000,
            "Violent crime total": 3370,
            "Murder and nonnegligent Manslaughter": 32,
            "Legacy rape /1": 186,
            "Revised rape /2": "",
            "Robbery": 737,
            "Aggravated assault": 2415,
            "Property crime total": 35067,
            "Burglary": 8698,
            "Larceny-theft": 23891,
            "Motor vehicle theft": 2478,
            "Violent Crime rate": 559.8,
            "Murder and nonnegligent manslaughter rate": 5.3,
            "Legacy rape rate /1": 30.9,
            "Robbery rate": 122.4,
            "Aggravated assault rate": 401.2,
            "Property crime rate": 5825.1,
            "Burglary rate": 1444.9,
            "Larceny-theft rate": 3968.6,
            "Motor vehicle theft rate": 411.6
          },
          {
            "Year": 1983,
            "Population": 606000,
            "Violent crime total": 2746,
            "Murder and nonnegligent Manslaughter": 25,
            "Legacy rape /1": 229,
            "Revised rape /2": "",
            "Robbery": 699,
            "Aggravated assault": 1793,
            "Property crime total": 30378,
            "Burglary": 7414,
            "Larceny-theft": 20908,
            "Motor vehicle theft": 2056,
            "Violent Crime rate": 453.1,
            "Murder and nonnegligent manslaughter rate": 4.1,
            "Legacy rape rate /1": 37.8,
            "Robbery rate": 115.3,
            "Aggravated assault rate": 295.9,
            "Property crime rate": 5012.9,
            "Burglary rate": 1223.4,
            "Larceny-theft rate": 3450.2,
            "Motor vehicle theft rate": 339.3
          },
          {
            "Year": 1984,
            "Population": 613000,
            "Violent crime total": 2671,
            "Murder and nonnegligent Manslaughter": 25,
            "Legacy rape /1": 300,
            "Revised rape /2": "",
            "Robbery": 711,
            "Aggravated assault": 1635,
            "Property crime total": 28021,
            "Burglary": 6678,
            "Larceny-theft": 19747,
            "Motor vehicle theft": 1596,
            "Violent Crime rate": 435.7,
            "Murder and nonnegligent manslaughter rate": 4.1,
            "Legacy rape rate /1": 48.9,
            "Robbery rate": 116,
            "Aggravated assault rate": 266.7,
            "Property crime rate": 4571.1,
            "Burglary rate": 1089.4,
            "Larceny-theft rate": 3221.4,
            "Motor vehicle theft rate": 260.4
          },
          {
            "Year": 1985,
            "Population": 622000,
            "Violent crime total": 2695,
            "Murder and nonnegligent Manslaughter": 30,
            "Legacy rape /1": 296,
            "Revised rape /2": "",
            "Robbery": 773,
            "Aggravated assault": 1596,
            "Property crime total": 28164,
            "Burglary": 6826,
            "Larceny-theft": 19638,
            "Motor vehicle theft": 1700,
            "Violent Crime rate": 433.3,
            "Murder and nonnegligent manslaughter rate": 4.8,
            "Legacy rape rate /1": 47.6,
            "Robbery rate": 124.3,
            "Aggravated assault rate": 256.6,
            "Property crime rate": 4528,
            "Burglary rate": 1097.4,
            "Larceny-theft rate": 3157.2,
            "Motor vehicle theft rate": 273.3
          },
          {
            "Year": 1986,
            "Population": 633000,
            "Violent crime total": 2703,
            "Murder and nonnegligent Manslaughter": 31,
            "Legacy rape /1": 360,
            "Revised rape /2": "",
            "Robbery": 786,
            "Aggravated assault": 1526,
            "Property crime total": 27881,
            "Burglary": 6598,
            "Larceny-theft": 19562,
            "Motor vehicle theft": 1721,
            "Violent Crime rate": 427,
            "Murder and nonnegligent manslaughter rate": 4.9,
            "Legacy rape rate /1": 56.9,
            "Robbery rate": 124.2,
            "Aggravated assault rate": 241.1,
            "Property crime rate": 4404.6,
            "Burglary rate": 1042.3,
            "Larceny-theft rate": 3090.4,
            "Motor vehicle theft rate": 271.9
          },
          {
            "Year": 1987,
            "Population": 644000,
            "Violent crime total": 2774,
            "Murder and nonnegligent Manslaughter": 33,
            "Legacy rape /1": 441,
            "Revised rape /2": "",
            "Robbery": 789,
            "Aggravated assault": 1511,
            "Property crime total": 29032,
            "Burglary": 6572,
            "Larceny-theft": 20453,
            "Motor vehicle theft": 2007,
            "Violent Crime rate": 430.7,
            "Murder and nonnegligent manslaughter rate": 5.1,
            "Legacy rape rate /1": 68.5,
            "Robbery rate": 122.5,
            "Aggravated assault rate": 234.6,
            "Property crime rate": 4508.1,
            "Burglary rate": 1020.5,
            "Larceny-theft rate": 3175.9,
            "Motor vehicle theft rate": 311.6
          },
          {
            "Year": 1988,
            "Population": 660000,
            "Violent crime total": 2981,
            "Murder and nonnegligent Manslaughter": 34,
            "Legacy rape /1": 491,
            "Revised rape /2": "",
            "Robbery": 784,
            "Aggravated assault": 1672,
            "Property crime total": 28693,
            "Burglary": 6868,
            "Larceny-theft": 19824,
            "Motor vehicle theft": 2001,
            "Violent Crime rate": 451.7,
            "Murder and nonnegligent manslaughter rate": 5.2,
            "Legacy rape rate /1": 74.4,
            "Robbery rate": 118.8,
            "Aggravated assault rate": 253.3,
            "Property crime rate": 4347.4,
            "Burglary rate": 1040.6,
            "Larceny-theft rate": 3003.6,
            "Motor vehicle theft rate": 303.2
          },
          {
            "Year": 1989,
            "Population": 673000,
            "Violent crime total": 3745,
            "Murder and nonnegligent Manslaughter": 34,
            "Legacy rape /1": 569,
            "Revised rape /2": "",
            "Robbery": 934,
            "Aggravated assault": 2208,
            "Property crime total": 28998,
            "Burglary": 6072,
            "Larceny-theft": 20294,
            "Motor vehicle theft": 2632,
            "Violent Crime rate": 556.5,
            "Murder and nonnegligent manslaughter rate": 5.1,
            "Legacy rape rate /1": 84.5,
            "Robbery rate": 138.8,
            "Aggravated assault rate": 328.1,
            "Property crime rate": 4308.8,
            "Burglary rate": 902.2,
            "Larceny-theft rate": 3015.5,
            "Motor vehicle theft rate": 391.1
          },
          {
            "Year": 1990,
            "Population": 666168,
            "Violent crime total": 4365,
            "Murder and nonnegligent Manslaughter": 33,
            "Legacy rape /1": 587,
            "Revised rape /2": "",
            "Robbery": 1098,
            "Aggravated assault": 2647,
            "Property crime total": 31344,
            "Burglary": 6465,
            "Larceny-theft": 21922,
            "Motor vehicle theft": 2957,
            "Violent Crime rate": 655.2,
            "Murder and nonnegligent manslaughter rate": 5,
            "Legacy rape rate /1": 88.1,
            "Robbery rate": 164.8,
            "Aggravated assault rate": 397.3,
            "Property crime rate": 4705.1,
            "Burglary rate": 970.5,
            "Larceny-theft rate": 3290.8,
            "Motor vehicle theft rate": 443.9
          },
          {
            "Year": 1991,
            "Population": 680000,
            "Violent crime total": 4857,
            "Murder and nonnegligent Manslaughter": 37,
            "Legacy rape /1": 588,
            "Revised rape /2": "",
            "Robbery": 1460,
            "Aggravated assault": 2772,
            "Property crime total": 35055,
            "Burglary": 7668,
            "Larceny-theft": 24836,
            "Motor vehicle theft": 2551,
            "Violent Crime rate": 714.3,
            "Murder and nonnegligent manslaughter rate": 5.4,
            "Legacy rape rate /1": 86.5,
            "Robbery rate": 214.7,
            "Aggravated assault rate": 407.6,
            "Property crime rate": 5155.1,
            "Burglary rate": 1127.6,
            "Larceny-theft rate": 3652.4,
            "Motor vehicle theft rate": 375.1
          },
          {
            "Year": 1992,
            "Population": 689000,
            "Violent crime total": 4280,
            "Murder and nonnegligent Manslaughter": 32,
            "Legacy rape /1": 591,
            "Revised rape /2": "",
            "Robbery": 1042,
            "Aggravated assault": 2615,
            "Property crime total": 29126,
            "Burglary": 6598,
            "Larceny-theft": 20419,
            "Motor vehicle theft": 2109,
            "Violent Crime rate": 621.2,
            "Murder and nonnegligent manslaughter rate": 4.6,
            "Legacy rape rate /1": 85.8,
            "Robbery rate": 151.2,
            "Aggravated assault rate": 379.5,
            "Property crime rate": 4227.3,
            "Burglary rate": 957.6,
            "Larceny-theft rate": 2963.6,
            "Motor vehicle theft rate": 306.1
          },
          {
            "Year": 1993,
            "Population": 700000,
            "Violent crime total": 4801,
            "Murder and nonnegligent Manslaughter": 35,
            "Legacy rape /1": 539,
            "Revised rape /2": "",
            "Robbery": 1307,
            "Aggravated assault": 2920,
            "Property crime total": 29304,
            "Burglary": 6244,
            "Larceny-theft": 20853,
            "Motor vehicle theft": 2207,
            "Violent Crime rate": 685.9,
            "Murder and nonnegligent manslaughter rate": 5,
            "Legacy rape rate /1": 77,
            "Robbery rate": 186.7,
            "Aggravated assault rate": 417.1,
            "Property crime rate": 4186.3,
            "Burglary rate": 892,
            "Larceny-theft rate": 2979,
            "Motor vehicle theft rate": 315.3
          },
          {
            "Year": 1994,
            "Population": 706000,
            "Violent crime total": 4549,
            "Murder and nonnegligent Manslaughter": 33,
            "Legacy rape /1": 546,
            "Revised rape /2": "",
            "Robbery": 1141,
            "Aggravated assault": 2829,
            "Property crime total": 29971,
            "Burglary": 6198,
            "Larceny-theft": 20828,
            "Motor vehicle theft": 2945,
            "Violent Crime rate": 644.3,
            "Murder and nonnegligent manslaughter rate": 4.7,
            "Legacy rape rate /1": 77.3,
            "Robbery rate": 161.6,
            "Aggravated assault rate": 400.7,
            "Property crime rate": 4245.2,
            "Burglary rate": 877.9,
            "Larceny-theft rate": 2950.1,
            "Motor vehicle theft rate": 417.1
          },
          {
            "Year": 1995,
            "Population": 717000,
            "Violent crime total": 5198,
            "Murder and nonnegligent Manslaughter": 25,
            "Legacy rape /1": 575,
            "Revised rape /2": "",
            "Robbery": 1425,
            "Aggravated assault": 3173,
            "Property crime total": 31790,
            "Burglary": 6491,
            "Larceny-theft": 22329,
            "Motor vehicle theft": 2970,
            "Violent Crime rate": 725,
            "Murder and nonnegligent manslaughter rate": 3.5,
            "Legacy rape rate /1": 80.2,
            "Robbery rate": 198.7,
            "Aggravated assault rate": 442.5,
            "Property crime rate": 4433.8,
            "Burglary rate": 905.3,
            "Larceny-theft rate": 3114.2,
            "Motor vehicle theft rate": 414.2
          },
          {
            "Year": 1996,
            "Population": 725000,
            "Violent crime total": 4845,
            "Murder and nonnegligent Manslaughter": 31,
            "Legacy rape /1": 454,
            "Revised rape /2": "",
            "Robbery": 1304,
            "Aggravated assault": 3056,
            "Property crime total": 30643,
            "Burglary": 5830,
            "Larceny-theft": 21665,
            "Motor vehicle theft": 3148,
            "Violent Crime rate": 668.3,
            "Murder and nonnegligent manslaughter rate": 4.3,
            "Legacy rape rate /1": 62.6,
            "Robbery rate": 179.9,
            "Aggravated assault rate": 421.5,
            "Property crime rate": 4226.6,
            "Burglary rate": 804.1,
            "Larceny-theft rate": 2988.3,
            "Motor vehicle theft rate": 434.2
          },
          {
            "Year": 1997,
            "Population": 732000,
            "Violent crime total": 5753,
            "Murder and nonnegligent Manslaughter": 22,
            "Legacy rape /1": 428,
            "Revised rape /2": "",
            "Robbery": 1783,
            "Aggravated assault": 3520,
            "Property crime total": 36578,
            "Burglary": 6421,
            "Larceny-theft": 25904,
            "Motor vehicle theft": 4253,
            "Violent Crime rate": 785.9,
            "Murder and nonnegligent manslaughter rate": 3,
            "Legacy rape rate /1": 58.5,
            "Robbery rate": 243.6,
            "Aggravated assault rate": 480.9,
            "Property crime rate": 4997,
            "Burglary rate": 877.2,
            "Larceny-theft rate": 3538.8,
            "Motor vehicle theft rate": 581
          },
          {
            "Year": 1998,
            "Population": 744000,
            "Violent crime total": 5672,
            "Murder and nonnegligent Manslaughter": 21,
            "Legacy rape /1": 499,
            "Revised rape /2": "",
            "Robbery": 1445,
            "Aggravated assault": 3707,
            "Property crime total": 34230,
            "Burglary": 6395,
            "Larceny-theft": 24649,
            "Motor vehicle theft": 3186,
            "Violent Crime rate": 762.4,
            "Murder and nonnegligent manslaughter rate": 2.8,
            "Legacy rape rate /1": 67.1,
            "Robbery rate": 194.2,
            "Aggravated assault rate": 498.3,
            "Property crime rate": 4600.8,
            "Burglary rate": 859.5,
            "Larceny-theft rate": 3313,
            "Motor vehicle theft rate": 428.2
          },
          {
            "Year": 1999,
            "Population": 753538,
            "Violent crime total": 5534,
            "Murder and nonnegligent Manslaughter": 24,
            "Legacy rape /1": 529,
            "Revised rape /2": "",
            "Robbery": 1492,
            "Aggravated assault": 3489,
            "Property crime total": 30922,
            "Burglary": 5245,
            "Larceny-theft": 22634,
            "Motor vehicle theft": 3043,
            "Violent Crime rate": 734.4,
            "Murder and nonnegligent manslaughter rate": 3.2,
            "Legacy rape rate /1": 70.2,
            "Robbery rate": 198,
            "Aggravated assault rate": 463,
            "Property crime rate": 4103.6,
            "Burglary rate": 696,
            "Larceny-theft rate": 3003.7,
            "Motor vehicle theft rate": 403.8
          },
          {
            "Year": 2000,
            "Population": 783600,
            "Violent crime total": 5363,
            "Murder and nonnegligent Manslaughter": 25,
            "Legacy rape /1": 424,
            "Revised rape /2": "",
            "Robbery": 1394,
            "Aggravated assault": 3520,
            "Property crime total": 29727,
            "Burglary": 5216,
            "Larceny-theft": 21360,
            "Motor vehicle theft": 3151,
            "Violent Crime rate": 684.4,
            "Murder and nonnegligent manslaughter rate": 3.2,
            "Legacy rape rate /1": 54.1,
            "Robbery rate": 177.9,
            "Aggravated assault rate": 449.2,
            "Property crime rate": 3793.6,
            "Burglary rate": 665.6,
            "Larceny-theft rate": 2725.9,
            "Motor vehicle theft rate": 402.1
          },
          {
            "Year": 2001,
            "Population": 796599,
            "Violent crime total": 4868,
            "Murder and nonnegligent Manslaughter": 23,
            "Legacy rape /1": 420,
            "Revised rape /2": "",
            "Robbery": 1156,
            "Aggravated assault": 3269,
            "Property crime total": 27399,
            "Burglary": 5144,
            "Larceny-theft": 19476,
            "Motor vehicle theft": 2779,
            "Violent Crime rate": 611.1,
            "Murder and nonnegligent manslaughter rate": 2.9,
            "Legacy rape rate /1": 52.7,
            "Robbery rate": 145.1,
            "Aggravated assault rate": 410.4,
            "Property crime rate": 3439.5,
            "Burglary rate": 645.7,
            "Larceny-theft rate": 2444.9,
            "Motor vehicle theft rate": 348.9
          },
          {
            "Year": 2002,
            "Population": 805945,
            "Violent crime total": 4836,
            "Murder and nonnegligent Manslaughter": 26,
            "Legacy rape /1": 358,
            "Revised rape /2": "",
            "Robbery": 1154,
            "Aggravated assault": 3298,
            "Property crime total": 26967,
            "Burglary": 5355,
            "Larceny-theft": 18555,
            "Motor vehicle theft": 3057,
            "Violent Crime rate": 600,
            "Murder and nonnegligent manslaughter rate": 3.2,
            "Legacy rape rate /1": 44.4,
            "Robbery rate": 143.2,
            "Aggravated assault rate": 409.2,
            "Property crime rate": 3346,
            "Burglary rate": 664.4,
            "Larceny-theft rate": 2302.3,
            "Motor vehicle theft rate": 379.3
          },
          {
            "Year": 2003,
            "Population": 818166,
            "Violent crime total": 5525,
            "Murder and nonnegligent Manslaughter": 21,
            "Legacy rape /1": 370,
            "Revised rape /2": "",
            "Robbery": 1441,
            "Aggravated assault": 3693,
            "Property crime total": 27943,
            "Burglary": 6066,
            "Larceny-theft": 18933,
            "Motor vehicle theft": 2944,
            "Violent Crime rate": 675.3,
            "Murder and nonnegligent manslaughter rate": 2.6,
            "Legacy rape rate /1": 45.2,
            "Robbery rate": 176.1,
            "Aggravated assault rate": 451.4,
            "Property crime rate": 3415.3,
            "Burglary rate": 741.4,
            "Larceny-theft rate": 2314.1,
            "Motor vehicle theft rate": 359.8
          },
          {
            "Year": 2004,
            "Population": 830069,
            "Violent crime total": 5105,
            "Murder and nonnegligent Manslaughter": 28,
            "Legacy rape /1": 357,
            "Revised rape /2": "",
            "Robbery": 1343,
            "Aggravated assault": 3377,
            "Property crime total": 27256,
            "Burglary": 5669,
            "Larceny-theft": 19285,
            "Motor vehicle theft": 2302,
            "Violent Crime rate": 615,
            "Murder and nonnegligent manslaughter rate": 3.4,
            "Legacy rape rate /1": 43,
            "Robbery rate": 161.8,
            "Aggravated assault rate": 406.8,
            "Property crime rate": 3283.6,
            "Burglary rate": 683,
            "Larceny-theft rate": 2323.3,
            "Motor vehicle theft rate": 277.3
          },
          {
            "Year": 2005,
            "Population": 841741,
            "Violent crime total": 5332,
            "Murder and nonnegligent Manslaughter": 37,
            "Legacy rape /1": 377,
            "Revised rape /2": "",
            "Robbery": 1306,
            "Aggravated assault": 3612,
            "Property crime total": 26245,
            "Burglary": 5811,
            "Larceny-theft": 18085,
            "Motor vehicle theft": 2349,
            "Violent Crime rate": 633,
            "Murder and nonnegligent manslaughter rate": 4.4,
            "Legacy rape rate /1": 44.8,
            "Robbery rate": 155.2,
            "Aggravated assault rate": 429.1,
            "Property crime rate": 3118,
            "Burglary rate": 690.4,
            "Larceny-theft rate": 2148,
            "Motor vehicle theft rate": 279
          },
          {
            "Year": 2006,
            "Population": 853476,
            "Violent crime total": 5983,
            "Murder and nonnegligent Manslaughter": 42,
            "Legacy rape /1": 417,
            "Revised rape /2": "",
            "Robbery": 1791,
            "Aggravated assault": 3733,
            "Property crime total": 29670,
            "Burglary": 6337,
            "Larceny-theft": 20449,
            "Motor vehicle theft": 2884,
            "Violent Crime rate": 701,
            "Murder and nonnegligent manslaughter rate": 4.9,
            "Legacy rape rate /1": 48.9,
            "Robbery rate": 209.8,
            "Aggravated assault rate": 437.4,
            "Property crime rate": 3476.4,
            "Burglary rate": 742.5,
            "Larceny-theft rate": 2396,
            "Motor vehicle theft rate": 337.9
          },
          {
            "Year": 2007,
            "Population": 864764,
            "Violent crime total": 6100,
            "Murder and nonnegligent Manslaughter": 39,
            "Legacy rape /1": 341,
            "Revised rape /2": "",
            "Robbery": 1763,
            "Aggravated assault": 3957,
            "Property crime total": 29216,
            "Burglary": 6420,
            "Larceny-theft": 20454,
            "Motor vehicle theft": 2342,
            "Violent Crime rate": 705.4,
            "Murder and nonnegligent manslaughter rate": 4.5,
            "Legacy rape rate /1": 39.4,
            "Robbery rate": 203.9,
            "Aggravated assault rate": 457.6,
            "Property crime rate": 3378.5,
            "Burglary rate": 742.4,
            "Larceny-theft rate": 2365.3,
            "Motor vehicle theft rate": 270.8
          },
          {
            "Year": 2008,
            "Population": 873092,
            "Violent crime total": 6187,
            "Murder and nonnegligent Manslaughter": 57,
            "Legacy rape /1": 371,
            "Revised rape /2": "",
            "Robbery": 1847,
            "Aggravated assault": 3912,
            "Property crime total": 31385,
            "Burglary": 6783,
            "Larceny-theft": 22045,
            "Motor vehicle theft": 2557,
            "Violent Crime rate": 708.6,
            "Murder and nonnegligent manslaughter rate": 6.5,
            "Legacy rape rate /1": 42.5,
            "Robbery rate": 211.5,
            "Aggravated assault rate": 448.1,
            "Property crime rate": 3594.7,
            "Burglary rate": 776.9,
            "Larceny-theft rate": 2524.9,
            "Motor vehicle theft rate": 292.9
          },
          {
            "Year": 2009,
            "Population": 885122,
            "Violent crime total": 5713,
            "Murder and nonnegligent Manslaughter": 41,
            "Legacy rape /1": 395,
            "Revised rape /2": "",
            "Robbery": 1680,
            "Aggravated assault": 3597,
            "Property crime total": 29685,
            "Burglary": 6943,
            "Larceny-theft": 20836,
            "Motor vehicle theft": 1906,
            "Violent Crime rate": 645.4,
            "Murder and nonnegligent manslaughter rate": 4.6,
            "Legacy rape rate /1": 44.6,
            "Robbery rate": 189.8,
            "Aggravated assault rate": 406.4,
            "Property crime rate": 3353.8,
            "Burglary rate": 784.4,
            "Larceny-theft rate": 2354,
            "Motor vehicle theft rate": 215.3
          },
          {
            "Year": 2010,
            "Population": 899792,
            "Violent crime total": 5608,
            "Murder and nonnegligent Manslaughter": 51,
            "Legacy rape /1": 326,
            "Revised rape /2": "",
            "Robbery": 1839,
            "Aggravated assault": 3392,
            "Property crime total": 31078,
            "Burglary": 7550,
            "Larceny-theft": 21593,
            "Motor vehicle theft": 1935,
            "Violent Crime rate": 623.3,
            "Murder and nonnegligent manslaughter rate": 5.7,
            "Legacy rape rate /1": 36.2,
            "Robbery rate": 204.4,
            "Aggravated assault rate": 377,
            "Property crime rate": 3453.9,
            "Burglary rate": 839.1,
            "Larceny-theft rate": 2399.8,
            "Motor vehicle theft rate": 215
          },
          {
            "Year": 2011,
            "Population": 908137,
            "Violent crime total": 5144,
            "Murder and nonnegligent Manslaughter": 48,
            "Legacy rape /1": 307,
            "Revised rape /2": "",
            "Robbery": 1558,
            "Aggravated assault": 3231,
            "Property crime total": 31163,
            "Burglary": 7617,
            "Larceny-theft": 22001,
            "Motor vehicle theft": 1545,
            "Violent Crime rate": 566.4,
            "Murder and nonnegligent manslaughter rate": 5.3,
            "Legacy rape rate /1": 33.8,
            "Robbery rate": 171.6,
            "Aggravated assault rate": 355.8,
            "Property crime rate": 3431.5,
            "Burglary rate": 838.8,
            "Larceny-theft rate": 2422.7,
            "Motor vehicle theft rate": 170.1
          },
          {
            "Year": 2012,
            "Population": 917053,
            "Violent crime total": 5048,
            "Murder and nonnegligent Manslaughter": 56,
            "Legacy rape /1": 249,
            "Revised rape /2": "",
            "Robbery": 1498,
            "Aggravated assault": 3245,
            "Property crime total": 30707,
            "Burglary": 7389,
            "Larceny-theft": 21880,
            "Motor vehicle theft": 1438,
            "Violent Crime rate": 550.5,
            "Murder and nonnegligent manslaughter rate": 6.1,
            "Legacy rape rate /1": 27.2,
            "Robbery rate": 163.3,
            "Aggravated assault rate": 353.9,
            "Property crime rate": 3348.4,
            "Burglary rate": 805.7,
            "Larceny-theft rate": 2385.9,
            "Motor vehicle theft rate": 156.8
          },
          {
            "Year": 2013,
            "Population": 925240,
            "Violent crime total": 4633,
            "Murder and nonnegligent Manslaughter": 41,
            "Legacy rape /1": 278,
            "Revised rape /2": 399,
            "Robbery": 1233,
            "Aggravated assault": 2960,
            "Property crime total": 29001,
            "Burglary": 6299,
            "Larceny-theft": 21347,
            "Motor vehicle theft": 1355,
            "Violent Crime rate": 500.7,
            "Murder and nonnegligent manslaughter rate": 4.4,
            "Legacy rape rate /1": 30,
            "Robbery rate": 133.3,
            "Aggravated assault rate": 319.9,
            "Property crime rate": 3134.4,
            "Burglary rate": 680.8,
            "Larceny-theft rate": 2307.2,
            "Motor vehicle theft rate": 146.4
          },
          {
            "Year": 2014,
            "Population": 935614,
            "Violent crime total": 4576,
            "Murder and nonnegligent Manslaughter": 54,
            "Legacy rape /1": 249,
            "Revised rape /2": 386,
            "Robbery": 1269,
            "Aggravated assault": 2867,
            "Property crime total": 27900,
            "Burglary": 5768,
            "Larceny-theft": 20865,
            "Motor vehicle theft": 1267,
            "Violent Crime rate": 489.1,
            "Murder and nonnegligent manslaughter rate": 5.8,
            "Legacy rape rate /1": 26.6,
            "Robbery rate": 135.6,
            "Aggravated assault rate": 306.4,
            "Property crime rate": 2982,
            "Burglary rate": 616.5,
            "Larceny-theft rate": 2230.1,
            "Motor vehicle theft rate": 135.4
          }
        ]
}